agentguard/__init__.py
agentguard/client.py
agentguard/policy.py
agentguard/types.py
agentguard/clients/__init__.py
agentguard/clients/guarded_anthropic.py
agentguard/clients/guarded_azure_openai.py
agentguard/clients/guarded_openai.py
agentguard/cost/__init__.py
agentguard/cost/budget.py
agentguard/cost/pricing.py
agentguard/cost/storage.py
agentguard/cost/tracker.py
agentguard/cost/types.py
agentguard/cost/utils.py
agentguard/guardrails/__init__.py
agentguard/guardrails/base.py
agentguard/guardrails/content_moderation.py
agentguard/guardrails/engine.py
agentguard/guardrails/pii_detection.py
agentguard/guardrails/prompt_injection.py
agentguard_sdk-0.2.2.dist-info/METADATA
agentguard_sdk-0.2.2.dist-info/WHEEL
agentguard_sdk-0.2.2.dist-info/licenses/LICENSE
agentguard_sdk-0.2.2.dist-info/RECORD
