Metadata-Version: 2.4
Name: agentguard-sdk
Version: 0.2.2
Summary: Python SDK for AI Agent Security Platform
Project-URL: Homepage, https://github.com/agentguard-ai/agentguard-python
Project-URL: Documentation, https://github.com/agentguard-ai/agentguard-python#readme
Project-URL: Repository, https://github.com/agentguard-ai/agentguard-python
Project-URL: Issues, https://github.com/agentguard-ai/agentguard-python/issues
Author-email: AgentGuard Team <agentguard@proton.me>
License: MIT
License-File: LICENSE
Keywords: agent,ai,anthropic,audit,automation,chatbot,claude,compliance,governance,guardrails,langchain,llm,middleware,openai,policy,protection,python,sdk,security
Classifier: Development Status :: 4 - Beta
Classifier: Intended Audience :: Developers
Classifier: License :: OSI Approved :: MIT License
Classifier: Programming Language :: Python :: 3
Classifier: Programming Language :: Python :: 3.8
Classifier: Programming Language :: Python :: 3.9
Classifier: Programming Language :: Python :: 3.10
Classifier: Programming Language :: Python :: 3.11
Classifier: Programming Language :: Python :: 3.12
Classifier: Topic :: Security
Classifier: Topic :: Software Development :: Libraries :: Python Modules
Classifier: Typing :: Typed
Requires-Python: >=3.8
Requires-Dist: anthropic>=0.18.0
Requires-Dist: httpx>=0.25.0
Requires-Dist: openai>=1.0.0
Requires-Dist: pydantic>=2.0.0
Provides-Extra: dev
Requires-Dist: black>=23.7.0; extra == 'dev'
Requires-Dist: hypothesis>=6.0.0; extra == 'dev'
Requires-Dist: isort>=5.12.0; extra == 'dev'
Requires-Dist: mypy>=1.5.0; extra == 'dev'
Requires-Dist: pytest-asyncio>=0.21.0; extra == 'dev'
Requires-Dist: pytest-cov>=4.1.0; extra == 'dev'
Requires-Dist: pytest>=7.4.0; extra == 'dev'
Requires-Dist: ruff>=0.0.285; extra == 'dev'
